nic_notify/__init__.py
nic_notify/__main__.py
nic_notify/admin.py
nic_notify/apps.py
nic_notify/cli.py
nic_notify/models.py
nic_notify/urls.py
nic_notify/utils.py
nic_notify/email/receive.py
nic_notify/email/send.py
nic_notify/email/urls.py
nic_notify/whatsapp/receive.py
nic_notify/whatsapp/send.py
nic_notify/whatsapp/urls.py
nic_notify-1.0.2.dist-info/licenses/LICENSE
nic_notify-1.0.2.dist-info/METADATA
nic_notify-1.0.2.dist-info/WHEEL
nic_notify-1.0.2.dist-info/entry_points.txt
nic_notify-1.0.2.dist-info/top_level.txt
nic_notify-1.0.2.dist-info/RECORD
